amsdal_models/Third-Party Materials - AMSDAL Dependencies - License Notices.md
amsdal_models/__about__.py
amsdal_models/__about__.pyi
amsdal_models/__init__.py
amsdal_models/__init__.pyi
amsdal_models/enums.py
amsdal_models/enums.pyi
amsdal_models/errors.py
amsdal_models/errors.pyi
amsdal_models/py.typed
amsdal_models/builder/__init__.py
amsdal_models/builder/__init__.pyi
amsdal_models/builder/class_source_builder.py
amsdal_models/builder/class_source_builder.pyi
amsdal_models/builder/utils.py
amsdal_models/builder/utils.pyi
amsdal_models/builder/validator_resolver.py
amsdal_models/builder/validator_resolver.pyi
amsdal_models/builder/ast_generator/__init__.py
amsdal_models/builder/ast_generator/__init__.pyi
amsdal_models/builder/ast_generator/class_generator.py
amsdal_models/builder/ast_generator/class_generator.pyi
amsdal_models/builder/ast_generator/data_models.py
amsdal_models/builder/ast_generator/data_models.pyi
amsdal_models/builder/ast_generator/dependency_generator.py
amsdal_models/builder/ast_generator/dependency_generator.pyi
amsdal_models/builder/ast_generator/helpers/__init__.py
amsdal_models/builder/ast_generator/helpers/__init__.pyi
amsdal_models/builder/ast_generator/helpers/build_annotation_node.py
amsdal_models/builder/ast_generator/helpers/build_annotation_node.pyi
amsdal_models/builder/ast_generator/helpers/build_assign_node.py
amsdal_models/builder/ast_generator/helpers/build_assign_node.pyi
amsdal_models/builder/ast_generator/helpers/build_dict_node.py
amsdal_models/builder/ast_generator/helpers/build_dict_node.pyi
amsdal_models/builder/ast_generator/helpers/build_validator_node.py
amsdal_models/builder/ast_generator/helpers/build_validator_node.pyi
amsdal_models/builder/services/__init__.py
amsdal_models/builder/services/__init__.pyi
amsdal_models/builder/services/class_builder.py
amsdal_models/builder/services/class_builder.pyi
amsdal_models/builder/validators/__init__.py
amsdal_models-0.5.33.dist-info/METADATA
amsdal_models-0.5.33.dist-info/WHEEL
amsdal_models-0.5.33.dist-info/top_level.txt
amsdal_models-0.5.33.dist-info/RECORD
amsdal_models-0.5.33.dist-info/licenses/LICENSE.txt
