Metadata-Version: 2.4
Name: amsdal_models
Version: 0.5.33
Summary: AMSDAL models
License: AMSDAL End User License Agreement
Project-URL: Documentation, https://pypi.org/project/amsdal-data/#readme
Project-URL: Issues, https://pypi.org/project/amsdal-data/
Project-URL: Source, https://pypi.org/project/amsdal-data/
Classifier: Development Status :: 4 - Beta
Classifier: Programming Language :: Python
Classifier: Programming Language :: Python :: 3.11
Classifier: Programming Language :: Python :: 3.12
Classifier: Programming Language :: Python :: 3.13
Classifier: Programming Language :: Python :: Implementation :: CPython
Classifier: Programming Language :: Python :: Implementation :: PyPy
Requires-Python: <3.14,>=3.11
License-File: LICENSE.txt
Requires-Dist: astor~=0.8
Requires-Dist: black>=24.3.0
Requires-Dist: ruff>=0.14.10
Requires-Dist: isort~=6.0
Requires-Dist: pydantic~=2.12
Requires-Dist: pandas~=2.1
Requires-Dist: pydantic-partial~=0.5
Requires-Dist: amsdal_utils==0.5.*
Requires-Dist: amsdal_data==0.5.*
Dynamic: license-file
